
  {
    "name": "First Training",
    "author": null,
    "cycles": [
      {
        "exercises": [
          {
            "exerciseReference": "api/exercise_references/1",
            "sets": [
              {
                "reps": 10,
                "weightPercent": 0,
                "weight": null
              },
              {
                "reps": 10,
                "weightPercent": 0,
                "weight": null
              }
            ],
            "restBetweenSet": 60,
            "executionStyle": "api/execution_styles/1"
          },
          {
            "exerciseReference": "api/exercise_references/2",
            "sets": [
              {
                "reps": 12,
                "weightPercent": 0.3,
                "weight": 150
              },
              {
                "reps": 12,
                "weightPercent": 0.3,
                "weight": 150
              },
              {
                "reps": 12,
                "weightPercent": 0.3,
                "weight": 150
              }
            ],
            "restBetweenSet": 60,
            "executionStyle": "api/execution_styles/2"
          }
        ],
        "restBetweenLoop": 180,
        "numberOfLoops": 1
      }
    ],
    "restBetweenCycles": 120
  }
